{
    "agent_id": "ExposureAggregator01",
    "timestamp": "2026-01-11T17:12:52",
    "executive_summary": "**Executive Summary: Customer Exposure Report Analysis**\n\nThe current accounts receivable (AR) exposure totals $1,407,216.61 across 10 customers, with an average exposure of $140,721.66 per customer. Of the 250 invoices outstanding, 150 (60%) are overdue, indicating elevated credit risk within the portfolio. This delinquency rate warrants immediate attention to mitigate potential financial losses and cash flow disruptions.\n\nThe top five customers account for approximately 64% of the total exposure, with Customer_1 ($263,516.36) and Customer_0 ($222,270.78) representing the largest individual risks. The concentration of exposure among a small number of customers heightens the portfolio\u2019s vulnerability to default risks, particularly if these key accounts face financial difficulties. Elevated AR balances from Customer_2 ($189,943.17), Customer_4 ($112,568.84), and Customer_7 ($109,582.97) further emphasize the need for proactive credit risk management.\n\nKey risk factors include the high proportion of overdue invoices, substantial exposure concentration among top customers, and potential liquidity challenges arising from delayed payments. These risks could adversely impact cash flow and operational stability if not addressed promptly.\n\n**Recommended Actions:**\n1. **Prioritize Collections**: Implement a targeted collections strategy for overdue invoices, focusing on high-exposure customers (e.g., Customer_1 and Customer_0).\n2. **Customer Risk Assessment**: Conduct a credit review of top-exposure customers to evaluate their financial health and payment reliability.\n3. **Payment Terms Review**: Reassess payment terms and enforce stricter credit controls, particularly for customers with recurring delinquency.\n4. **Portfolio Diversification**: Explore opportunities to reduce exposure concentration by acquiring additional customers or redistributing sales volume across existing accounts.\n\nProactive measures are essential to safeguard cash flow and reduce credit risk. Regular monitoring and engagement with high-risk customers will be critical in achieving financial stability.",
    "statistics": {
        "total_customers": 10,
        "total_exposure": 1407216.6099999999,
        "average_exposure": 140721.661,
        "total_invoices": 250,
        "overdue_invoices": 150
    }
}